{
  "catalog": [
    {
      "id": 1,
      "name": "Електроніка",
      "shortname": "electronics",
      "notes": ""
    },
    {
      "id": 2,
      "name": "Одяг",
      "shortname": "clothes",
      "notes": ""
    },
    {
      "id": 3,
      "name": "Книги",
      "shortname": "books",
      "notes": ""
    }
  ],
  "electronics": {
    "name": "Електроніка",
    "items": [
      {
        "id": 1,
        "name": "Смартфон",
        "shortname": "smartphone",
        "description": "Це сучасний смартфон з функціями камери, Wi-Fi, Bluetooth і т. д.",
        "price": "1000 USD"
      },
      {
        "id": 2,
        "name": "Ноутбук",
        "shortname": "laptop",
        "description": "Це потужний ноутбук з великим екраном і швидким процесором.",
        "price": "1500 USD"
      },
      {
        "id": 3,
        "name": "Телевізор",
        "shortname": "tv",
        "description": "Це великий телевізор з високою роздільною здатністю і сучасними технологіями.",
        "price": "2000 USD"
      },
      {
        "id": 4,
        "name": "Робот пилосос",
        "shortname": "vacuum",
        "description": "Робот пилосос для чистки дому з функцією GPS",
        "price": "1500 USD"
      }
    ]
  },
  "books": {
    "name": "Книги",
    "items": [
      {
        "id": 1,
        "name": "Гаррі Поттер і філософський камінь",
        "shortname": "harry_potter",
        "description": "Перша книга у серії про юного чарівника Гаррі Поттера та його пригоди в Школі чаклунства та чарівників.",
        "price": "15 USD"
      },
      {
        "id": 2,
        "name": "Метаморфози",
        "shortname": "metamorphosis",
        "description": "Роман Франца Кафки про перетворення Григорія Самси у комаху та його взаємодію з родиною.",
        "price": "22 USD"
      },
      {
        "id": 3,
        "name": "Шум і яр",
        "shortname": "the_sound_and_the_fury",
        "description": "Роман Вільяма Фолкнера про родину Комптонів і події у їхньому житті.",
        "price": "25 USD"
      },
      {
        "id": 4,
        "name": "1984",
        "shortname": "1984",
        "description": "Антиутопічний роман Джорджа Орвелла про суспільство, контроль і індивідуальність.",
        "price": "20 USD"
      }
    ]
  },
  "clothes": {
    "name": "Одяг",
    "items": [
      {
        "id": 1,
        "name": "Футболка",
        "shortname": "t_shirt",
        "description": "Класична футболка з коротким рукавом для щоденного використання.",
        "price": "10 USD"
      },
      {
        "id": 2,
        "name": "Джинси",
        "shortname": "jeans",
        "description": "Зручні та стильні джинси з високоякісного матеріалу.",
        "price": "30 USD"
      },
      {
        "id": 3,
        "name": "Світшот",
        "shortname": "sweatshirt",
        "description": "Комфортний світшот з м'якого матеріалу для прохолодних днів.",
        "price": "25 USD"
      },
      {
        "id": 4,
        "name": "Спортивні штани",
        "shortname": "sports_pants",
        "description": "Зручні та практичні штани для занять спортом.",
        "price": "20 USD"
      }
    ]
  }
}
